{
    "uuids": {
        "phone_id": "35c8f771-f601-45f8-bf7e-d63849e53fa6",
        "uuid": "f930687d-a442-4ae9-bf67-15785aeb0352",
        "client_session_id": "6c99cbb9-f242-4f81-9f27-2123b69db91d",
        "advertising_id": "46e09d05-634d-4d3d-8b76-56b753914c19",
        "android_device_id": "android-40766c0ff1f4f4f8",
        "request_id": "efcf2d33-32c5-43fb-a472-c95d0dd49e84",
        "tray_session_id": "4899ef10-71ad-4cea-9030-43a8047fb0f0"
    },
    "mid": "ahcMmAABAAHOBlUfG8BerzzqNB2m",
    "ig_u_rur": null,
    "ig_www_claim": null,
    "authorization_data": {
        "ds_user_id": "45916644374",
        "sessionid": "45916644374%3AYH8eFMvNvUW7jO%3A13%3AAYhNpNToAlMDdAH9hJwRfx3_2c450mBV4h28iaLcRA"
    },
    "cookies": {},
    "last_login": 1779895460.8190813,
    "device_settings": {
        "android_version": 34,
        "android_release": "14",
        "dpi": "480dpi",
        "resolution": "1344x2992",
        "manufacturer": "Google/google",
        "device": "husky",
        "model": "Pixel 8 Pro",
        "cpu": "husky",
        "app_version": "428.0.0.47.67",
        "version_code": "961145276",
        "bloks_versioning_id": "7189b949425f9bf80ea8bd880cf5a3080b292d9b1c4b38a18d112f7c4b71e7a8"
    },
    "user_agent": "Instagram 428.0.0.47.67 Android (34/14; 480dpi; 1344x2992; Google/google; Pixel 8 Pro; husky; husky; en_US; 961145276)",
    "country": "US",
    "country_code": 1,
    "locale": "en_US",
    "timezone_offset": -14400,
    "timezone_name": "GMT-04:00",
    "push_disabled": true,
    "request_timeout": 1,
    "public_request_retries_count": 3,
    "public_request_retries_timeout": 2,
    "session_retry_total": 3,
    "session_retry_backoff_factor": 2,
    "session_retry_statuses": [
        429,
        500,
        502,
        503,
        504
    ],
    "public_transport": "requests",
    "public_transport_impersonate": "chrome136",
    "tls_verify": true
}